{
  "meeting_id": 78,
  "title": "Ipo add panna meeting",
  "user_id": 5,
  "platform": "Zoom",
  "transcript_path": "/Users/shivayokeshwari/AI_Summariser/uploads/meeting_78_20251113T230538Z_New_transcript.txt",
  "generated_at": "2025-11-13T23:05:41.553446Z",
  "status": "ready",
  "summary_text": "AI Summariser Sprint Planning Meeting Transcript ---------------------------------------------------- Date: November 9, 2025 Platform: Zoom Project: AI Meeting Summariser – Sprint 3 Review Participants: - Aisha (Team…",
  "key_points": [
    "Backend summarization module is almost complete.",
    "Integration and deadlines for next week discussed.",
    "QA to cover error handling for empty or unreadable files.",
    "Internal demo for the Dean's Office scheduled for November 10th.",
    "Code-freeze after December 10th demo.",
    "Sprint 4 will focus on question-answer generation and cluster summaries.",
    "November 12th planning meeting scheduled.",
    "Progress review report due before the end of next week."
  ],
  "decisions": [
    "Finalize everything for the demo by November 10th at 9:00 PM.",
    "Code-freeze after December 10th at 9 PM demo.",
    "Prepare for November 12th planning meeting.",
    "Conduct review meeting on November 13th at 8:10 PM."
  ],
  "action_items": [
    "Nina to write regression cases by tomorrow.",
    "Arul to finish calendar connection UI and fix timezone error tonight.",
    "Sam to redeploy the containerized build tomorrow afternoon.",
    "Everyone to prepare ideas for embeddings by November 12th.",
    "Shiva to prepare backend metrics for the review meeting.",
    "Arul to include frontend screenshots and workflow demo.",
    "Nina to handle test coverage section.",
    "Sam to generate performance stats from Docker logs.",
    "Everyone to update tasks in Jira before the end of the day."
  ],
  "completed_at": "2025-11-13T23:05:49.144714Z"
}